pointcloud_utils/__init__.py
pointcloud_utils/calibration/__init__.py
pointcloud_utils/calibration/calibration.py
pointcloud_utils/calibration/calibration_kitti.py
pointcloud_utils/calibration/calibration_livox.py
pointcloud_utils/calibration/object3d_kitti.py
pointcloud_utils/calibration/transform.py
pointcloud_utils/io/__init__.py
pointcloud_utils/io/pointcloud_io.py
pointcloud_utils/ops/__init__.py
pointcloud_utils/ops/roiaware_pool3d/__init__.py
pointcloud_utils/ops/roiaware_pool3d/roiaware_pool3d_utils.py
pointcloud_utils/ros_utils/__init__.py
pointcloud_utils/ros_utils/ddynamic_reconfigure_python/__init__.py
pointcloud_utils/ros_utils/ddynamic_reconfigure_python/class_example.py
pointcloud_utils/ros_utils/ddynamic_reconfigure_python/ddynamic_reconfigure.py
pointcloud_utils/ros_utils/ddynamic_reconfigure_python/example.py
pointcloud_utils/ros_utils/ros2_numpy/__init__.py
pointcloud_utils/ros_utils/ros2_numpy/geometry.py
pointcloud_utils/ros_utils/ros2_numpy/image.py
pointcloud_utils/ros_utils/ros2_numpy/occupancy_grid.py
pointcloud_utils/ros_utils/ros2_numpy/point_cloud2.py
pointcloud_utils/ros_utils/ros2_numpy/registry.py
pointcloud_utils/ros_utils/ros_numpy/__init__.py
pointcloud_utils/ros_utils/ros_numpy/geometry.py
pointcloud_utils/ros_utils/ros_numpy/image.py
pointcloud_utils/ros_utils/ros_numpy/numpy_msg.py
pointcloud_utils/ros_utils/ros_numpy/occupancy_grid.py
pointcloud_utils/ros_utils/ros_numpy/point_cloud2.py
pointcloud_utils/ros_utils/ros_numpy/registry.py
pointcloud_utils/scenario_vis/stereo/dis2pointcloud.py
pointcloud_utils/visualization/__init__.py
pointcloud_utils/visualization/intensity_to_color.py
pointcloud_utils/visualization/o3d_viewer.py
ampcl-0.0.1.dist-info/METADATA
ampcl-0.0.1.dist-info/WHEEL
ampcl-0.0.1.dist-info/entry_points.txt
ampcl-0.0.1.dist-info/top_level.txt
ampcl-0.0.1.dist-info/RECORD
