Metadata-Version: 2.1
Name: ampcl
Version: 0.0.1
Summary: A small example package
Author-email: Hongqian Hunag <hong877381@gmail.com>
Project-URL: Homepage, https://github.com/Natsu-Akatsuki/PointCloud-PyUsage
Classifier: Programming Language :: Python :: 3
Classifier: Development Status :: 2 - Pre-Alpha
Classifier: Operating System :: Unix
Requires-Python: >=3.7
Requires-Dist: funcy
Requires-Dist: numba
Requires-Dist: requests
Requires-Dist: scipy (>=1.4)
Requires-Dist: setuptools (>=64.0)
Requires-Dist: open3d ; python_version < "3.10"
